py_graph_imputation_mlo/__init__.py
py_graph_imputation_mlo/filter_by_rest.py
py_graph_imputation_mlo/filter_top_3.py
py_graph_imputation_mlo/run_grim.py
py_graph_imputation_MLO-0.1.5.dist-info/LICENSE
py_graph_imputation_MLO-0.1.5.dist-info/METADATA
py_graph_imputation_MLO-0.1.5.dist-info/WHEEL
py_graph_imputation_MLO-0.1.5.dist-info/top_level.txt
py_graph_imputation_MLO-0.1.5.dist-info/RECORD
