Metadata-Version: 2.2
Name: py-graph-imputation-MLO
Version: 0.1.5
Author-email: Regev Yehezkel Imra <regevel2006@gmail.com>
License: MIT License
Classifier: Programming Language :: Python :: 3
Classifier: License :: OSI Approved :: MIT License
Requires-Python: >=3.8
License-File: LICENSE
Requires-Dist: py-graph-imputation
Requires-Dist: cython==0.29.32
Requires-Dist: numpy>=1.20.2
Requires-Dist: pandas
Requires-Dist: tqdm
